{
  "day": 21,
  "day_summary": {
    "title": "Day 21 Recitation Summary (Fatir 1-45, Ya-Sin 1-83, As-Saffat 1-182, Sad 1-88, Az-Zumar 1-31)",
    "summary": "Day 21 moves from Allah's creative power and human dependence in Fatir into resurrection certainty and revelation-centered warning in Ya-Sin, then through prophetic surrender, sacrifice, and repentance in As-Saffat and Sad. It closes in Az-Zumar with ikhlas, accountability, and the transforming effect of the Quran on hearts.",
    "themes": [
      "Creation signs and resurrection arguments restore certainty in Allah's absolute power and final return.",
      "Prophetic passages emphasize dua, patience, sacrifice, and repentance as lived servitude to Allah.",
      "Az-Zumar anchors sincere worship, fear-and-hope balance, and deep receptivity to revelation."
    ]
  },
  "highlights": [
    {
      "ayahRef": "35:15",
      "themeType": "Famous Ayah",
      "shortTitle": "All Need Allah",
      "whyNotable": [
        "A widely quoted ayah on ubudiyyah and human dependence before Allah.",
        "Frequently used in reminders on humility, sincerity, and reliance."
      ],
      "summary": "Allah declares that all people are in need of Him, while He alone is free of need and worthy of all praise. The ayah dismantles self-sufficiency and centers the believer on dependence upon Allah in every matter.",
      "keyTakeaway": "Build your worship and decisions on conscious need of Allah.",
      "references": [
        {
          "name": "Quran 35:15",
          "url": "https://quran.com/35:15"
        },
        {
          "name": "Ibn Kathir Tafsir (35:15)",
          "url": "https://quran.com/en/35:15/tafsirs/ar-tafsir-ibn-kathir"
        }
      ]
    },
    {
      "ayahRef": "36:58",
      "themeType": "Famous Ayah",
      "shortTitle": "Salam from the Most Merciful",
      "whyNotable": [
        "Among the most beloved Jannah ayat in public reminders and personal reflection.",
        "Often cited to cultivate hope in Allah's mercy and acceptance."
      ],
      "summary": "The people of Paradise are greeted with peace from a Lord full of mercy. The ayah presents ultimate success as being received by Allah's mercy, not by worldly standing.",
      "keyTakeaway": "Live with hope of Allah's merciful greeting in the Hereafter.",
      "references": [
        {
          "name": "Quran 36:58",
          "url": "https://quran.com/36:58"
        },
        {
          "name": "Ibn Kathir Tafsir (36:58)",
          "url": "https://quran.com/en/36:58/tafsirs/ar-tafsir-ibn-kathir"
        }
      ]
    },
    {
      "ayahRef": "36:82",
      "themeType": "Famous Ayah",
      "shortTitle": "Kun Fayakoon",
      "whyNotable": [
        "A foundational ayah frequently cited on qadr and divine power.",
        "Commonly recited to reinforce certainty when outcomes seem impossible."
      ],
      "summary": "Allah's command, when He wills a thing, is only to say 'Be,' and it is. The ayah establishes unrestricted divine authority over creation, resurrection, and every decree.",
      "keyTakeaway": "Trust Allah's power beyond visible causes.",
      "references": [
        {
          "name": "Quran 36:82",
          "url": "https://quran.com/36:82"
        },
        {
          "name": "Ibn Kathir Tafsir (36:82)",
          "url": "https://quran.com/en/36:82/tafsirs/ar-tafsir-ibn-kathir"
        }
      ]
    },
    {
      "ayahRef": "37:100",
      "themeType": "Dua",
      "shortTitle": "Ibrahim's Dua for Righteous Offspring",
      "whyNotable": [
        "A famous prophetic dua recited by parents and families.",
        "Represents faithful asking coupled with patience and surrender."
      ],
      "summary": "Ibrahim asks his Lord to grant him righteous offspring, and Allah gives glad tidings. The ayah models clear, sincere dua and trust in Allah's timing.",
      "keyTakeaway": "Ask Allah for righteous legacy with patience and certainty.",
      "references": [
        {
          "name": "Quran 37:100",
          "url": "https://quran.com/37:100"
        },
        {
          "name": "Ibn Kathir Tafsir (37:100)",
          "url": "https://quran.com/en/37:100/tafsirs/ar-tafsir-ibn-kathir"
        }
      ]
    },
    {
      "ayahRef": "38:35",
      "themeType": "Dua",
      "shortTitle": "Sulaiman's Dua with Istighfar",
      "whyNotable": [
        "A well-known dua combining repentance with purposeful request.",
        "Commonly referenced in lessons on adab of dua and leadership responsibility."
      ],
      "summary": "Sulaiman asks Allah for forgiveness and for a kingdom not granted to anyone after him. The ayah teaches beginning requests with repentance and seeking blessings for righteous service.",
      "keyTakeaway": "Open major requests with istighfar and right intention.",
      "references": [
        {
          "name": "Quran 38:35",
          "url": "https://quran.com/38:35"
        },
        {
          "name": "Ibn Kathir Tafsir (38:35)",
          "url": "https://quran.com/en/38:35/tafsirs/ar-tafsir-ibn-kathir"
        }
      ]
    },
    {
      "ayahRef": "39:23",
      "themeType": "Famous Ayah",
      "shortTitle": "The Best Speech",
      "whyNotable": [
        "A central ayah on how revelation should affect believing hearts.",
        "Widely cited in reminders on khushu, reflection, and transformative recitation."
      ],
      "summary": "Allah describes the Quran as the best speech, repeated and consistent, causing the skin of those who fear Him to tremble and then soften to Allah's remembrance. The ayah defines true engagement with revelation as a lived heart response.",
      "keyTakeaway": "Recite Quran for transformation, not routine completion.",
      "references": [
        {
          "name": "Quran 39:23",
          "url": "https://quran.com/39:23"
        },
        {
          "name": "Ibn Kathir Tafsir (39:23)",
          "url": "https://quran.com/en/39:23/tafsirs/ar-tafsir-ibn-kathir"
        }
      ]
    }
  ]
}
